sm_precursor_predictor/__init__.py
sm_precursor_predictor/data_integration/__init__.py
sm_precursor_predictor/data_integration/generate_kegg_networks.py
sm_precursor_predictor/data_integration/kegg_api.py
sm_precursor_predictor/data_integration/kegg_get_all_for_compound.py
sm_precursor_predictor/data_integration/kegg_precursor_finder.py
sm_precursor_predictor/prediction/__init__.py
sm_precursor_predictor/prediction/prediction.py
sm_precursor_predictor/prediction/ridge_classifier_layered_fingerprints_variance_selector/config.json
sm_precursor_predictor/prediction/ridge_classifier_layered_fingerprints_variance_selector/feature_selector.pkl
sm_precursor_predictor/prediction/ridge_classifier_layered_fingerprints_variance_selector/featurizer.pkl
sm_precursor_predictor/prediction/ridge_classifier_layered_fingerprints_variance_selector/pipeline.json
sm_precursor_predictor/prediction/ridge_classifier_layered_fingerprints_variance_selector/scaler.pkl
sm_precursor_predictor/prediction/ridge_classifier_layered_fingerprints_variance_selector/standardizer.pkl
sm_precursor_predictor/prediction/ridge_classifier_layered_fingerprints_variance_selector/model/model.pkl
sm_precursor_predictor/prediction/ridge_classifier_layered_fingerprints_variance_selector/model/model_params.pkl
sm_precursor_predictor/prediction/ridge_classifier_morgan_fp/config.json
sm_precursor_predictor/prediction/ridge_classifier_morgan_fp/morgan fingerprints.pkl
sm_precursor_predictor/prediction/ridge_classifier_morgan_fp/pipeline.json
sm_precursor_predictor/prediction/ridge_classifier_morgan_fp/model/model.pkl
sm_precursor_predictor/prediction/ridge_classifier_morgan_fp/model/model_params.pkl
SMPrecursorPrediction-0.0.2.dist-info/LICENSE
SMPrecursorPrediction-0.0.2.dist-info/METADATA
SMPrecursorPrediction-0.0.2.dist-info/WHEEL
SMPrecursorPrediction-0.0.2.dist-info/top_level.txt
SMPrecursorPrediction-0.0.2.dist-info/RECORD
